discord_py_role_panel_lib/__init__.py
discord_py_role_panel_lib/cm/role_panel_cm.py
discord_py_role_panel_lib/cmds/role_panel_cmd.py
discord_py_role_panel_lib/events/button_click_event.py
discord_py_role_panel_lib/events/buttons/0template_button_event.py
discord_py_role_panel_lib/events/buttons/role_panel_button_event.py
discord_py_role_panel_lib/events/components/normal_select_event.py
discord_py_role_panel_lib/utils/role_panel_function.py
discord_py_role_panel_lib-0.0.24.dist-info/LICENSE
discord_py_role_panel_lib-0.0.24.dist-info/METADATA
discord_py_role_panel_lib-0.0.24.dist-info/WHEEL
discord_py_role_panel_lib-0.0.24.dist-info/entry_points.txt
discord_py_role_panel_lib-0.0.24.dist-info/top_level.txt
discord_py_role_panel_lib-0.0.24.dist-info/RECORD
