Metadata-Version: 2.2
Name: discord-py-role-panel-lib
Version: 0.0.24
Summary: A library to assist with Discord.py development
Home-page: https://github.com/hashimotok-ecsv/discord-py-role-panel-lib
Download-URL: https://github.com/hashimotok-ecsv/discord-py-role-panel-lib
Author: hashimotok
Author-email: contact@hashimotok.dev
License: MIT
Project-URL: Documentation, https://discord-py-role-panel-lib.readthedocs.io/
Project-URL: Source, https://github.com/hashimotok-ecsv/discord-py-role-panel-lib
Project-URL: Tracker, https://github.com/hashimotok-ecsv/discord-py-role-panel-lib/issues
Keywords: discord.py role panel library
Classifier: Development Status :: 5 - Production/Stable
Classifier: Intended Audience :: Developers
Classifier: License :: OSI Approved :: MIT License
Classifier: Programming Language :: Python :: 3.10
Classifier: Programming Language :: Python :: 3.11
Classifier: Programming Language :: Python :: 3.12
Classifier: Operating System :: OS Independent
Requires-Python: >=3.10.6
License-File: LICENSE
Requires-Dist: discord.py>=2.5.2
Dynamic: author
Dynamic: author-email
Dynamic: classifier
Dynamic: description
Dynamic: description-content-type
Dynamic: download-url
Dynamic: home-page
Dynamic: keywords
Dynamic: license
Dynamic: project-url
Dynamic: requires-dist
Dynamic: requires-python
Dynamic: summary
